pek/__init__.py
pek/__main__.py
pek/version.py
pek/clustering/__init__.py
pek/clustering/ensemble.py
pek/clustering/interfaces.py
pek/clustering/process.py
pek/clustering/results.py
pek/clustering/run.py
pek/data/__init__.py
pek/data/__main__.py
pek/data/dataset.py
pek/data/folders.py
pek/data/importer.py
pek/data/loader.py
pek/data/projection.py
pek/data/_hdf5/A1.hdf5
pek/data/_hdf5/A2.hdf5
pek/data/_hdf5/A3.hdf5
pek/data/_hdf5/BalanceScale.hdf5
pek/data/_hdf5/ContraceptiveMethodChoice.hdf5
pek/data/_hdf5/Diabetes.hdf5
pek/data/_hdf5/Glass.hdf5
pek/data/_hdf5/HeartStatlog.hdf5
pek/data/_hdf5/Ionosphere.hdf5
pek/data/_hdf5/Iris.hdf5
pek/data/_hdf5/LiverDisorder.hdf5
pek/data/_hdf5/S1.hdf5
pek/data/_hdf5/S2.hdf5
pek/data/_hdf5/S3.hdf5
pek/data/_hdf5/S4.hdf5
pek/data/_hdf5/Segmentation.hdf5
pek/data/_hdf5/Sonar.hdf5
pek/data/_hdf5/SpectfHeart.hdf5
pek/data/_hdf5/Unbalanced.hdf5
pek/data/_hdf5/Vehicles.hdf5
pek/data/_hdf5/Wine.hdf5
pek/metrics/__init__.py
pek/metrics/comparison.py
pek/metrics/progression.py
pek/metrics/validation.py
pek/server/__init__.py
pek/server/__main__.py
pek/server/listener.py
pek/server/log.py
pek/server/server.py
pek/server/tasks.py
pek/server/wss.py
pek/termination/__init__.py
pek/termination/earlyTermination.py
pek/utils/__init__.py
pek/utils/clustering.py
pek/utils/encoding.py
pek/utils/params.py
pek/utils/process.py
pek/utils/random.py
pek-1.0.0.dist-info/LICENSE.txt
pek-1.0.0.dist-info/METADATA
pek-1.0.0.dist-info/WHEEL
pek-1.0.0.dist-info/top_level.txt
pek-1.0.0.dist-info/zip-safe
pek-1.0.0.dist-info/RECORD
