Metadata-Version: 2.1
Name: pek
Version: 1.0.0
Summary: PEK - Progressive Ensemble K-means clustering
Home-page: https://aware-diag-sapienza.github.io/pek
Download-URL: https://github.com/aware-diag-sapienza/pek/archive/refs/tags/v1.0.0.tar.gz
Author: A.WA.RE Research Group - Sapienza Università di Roma
Author-email: graziano.blasilli@uniroma1.it
License: CC-BY-NC-4.0
Platform: Linux
Platform: Mac OS-X
Platform: Solaris
Platform: Unix
Platform: Windows
Requires-Python: >=3.9.0
License-File: LICENSE.txt
Requires-Dist: scikit-learn >=1.3.0
Requires-Dist: numpy >=1.20.0
Requires-Dist: kneed >=0.8.0
Requires-Dist: flask >=3.0.0
Requires-Dist: flask-cors >=4.0.0
Requires-Dist: flask-socketio >=5.3.0
Requires-Dist: h5py
Requires-Dist: progressbar2
Requires-Dist: pandas
Requires-Dist: requests
Requires-Dist: downloader-cli
